audio_analyser
tests
